models_package_vasmoul/__init__.py
models_package_vasmoul/models.py
models_package_vasmoul-0.1.1.dist-info/METADATA
models_package_vasmoul-0.1.1.dist-info/WHEEL
models_package_vasmoul-0.1.1.dist-info/top_level.txt
models_package_vasmoul-0.1.1.dist-info/RECORD
