Metadata-Version: 2.4
Name: models_package_vasmoul
Version: 0.1.1
Summary: Django models for Project Management Dashboard
Author: Vasilis Moulopoulos
Author-email: vmoulop@gmail.com
Classifier: Programming Language :: Python :: 3
Classifier: Framework :: Django
Classifier: License :: OSI Approved :: MIT License
Classifier: Operating System :: OS Independent
Requires-Dist: Django>=4.2
Dynamic: author
Dynamic: author-email
Dynamic: classifier
Dynamic: description
Dynamic: description-content-type
Dynamic: requires-dist
Dynamic: summary
